robotar/__init__.py
robotar-0.0.2.dist-info/METADATA
robotar-0.0.2.dist-info/WHEEL
robotar-0.0.2.dist-info/top_level.txt
robotar-0.0.2.dist-info/RECORD
